jsonsyncer/__init__.py
jsonsyncer/_version.py
jsonsyncer/syncer.py
JsonSyncer-0.1.0.dist-info/LICENSE
JsonSyncer-0.1.0.dist-info/METADATA
JsonSyncer-0.1.0.dist-info/WHEEL
JsonSyncer-0.1.0.dist-info/top_level.txt
JsonSyncer-0.1.0.dist-info/RECORD
